{
	"animations": [
		{
			"offsets": [-32, 126],
			"loop": false,
			"fps": 24,
			"anim": "idle",
			"indices": [],
			"name": "Idle"
		},
		{
			"offsets": [-39, 115],
			"loop": false,
			"fps": 24,
			"anim": "singRIGHT",
			"indices": [],
			"name": "Right"
		},
		{
			"loop": false,
			"offsets": [44, 122],
			"anim": "singLEFT",
			"fps": 24,
			"name": "Left",
			"indices": []
		},
		{
			"offsets": [22, 111],
			"loop": false,
			"fps": 24,
			"anim": "singDOWN",
			"indices": [],
			"name": "Down"
		},
		{
			"offsets": [-31, 130],
			"loop": false,
			"fps": 24,
			"anim": "singUP",
			"indices": [],
			"name": "Up"
		},
		{
			"offsets": [82, 100],
			"loop": false,
			"fps": 24,
			"anim": "singLEFTmiss",
			"indices": [],
			"name": "MissLeft"
		},
		{
			"offsets": [23, 75],
			"loop": false,
			"fps": 24,
			"anim": "singDOWNmiss",
			"indices": [],
			"name": "MissDown"
		},
		{
			"offsets": [-37, 131],
			"loop": false,
			"fps": 24,
			"anim": "singRIGHTmiss",
			"indices": [],
			"name": "MissRight"
		},
		{
			"offsets": [-19, 119],
			"loop": false,
			"fps": 24,
			"anim": "singUPmiss",
			"indices": [],
			"name": "MissUp"
		}
	],
	"vocals_file": "",
	"no_antialiasing": false,
	"image": "characters/BeachYuwi",
	"position": [-270, 110],
	"healthicon": "yuwi",
	"flip_x": true,
	"healthbar_colors": [136, 48, 181],
	"camera_position": [-60, -40],
	"sing_duration": 4,
	"scale": 0.8,
	"_editor_isPlayer": true
}